pyaniml/__init__.py
pyaniml/core/__init__.py
pyaniml/core/animl.py
pyaniml/core/enums.py
pyaniml/core/experimentstep.py
pyaniml/core/infrastructure.py
pyaniml/core/method.py
pyaniml/core/parameter.py
pyaniml/core/result.py
pyaniml/core/sample.py
pyaniml/core/series.py
pyaniml/core/sets.py
pyaniml/core/unit.py
pyaniml/utility/__init__.py
pyaniml/utility/utils.py
pyAnIML-1.0.2.dist-info/LICENSE
pyAnIML-1.0.2.dist-info/METADATA
pyAnIML-1.0.2.dist-info/WHEEL
pyAnIML-1.0.2.dist-info/top_level.txt
pyAnIML-1.0.2.dist-info/RECORD
